os_cpu/__init__.py
os_cpu/tests/__init__.py
os_cpu/tests/base.py
os_cpu/tests/test_os_cpu.py
os_cpu-0.0.0.dist-info/DESCRIPTION.rst
os_cpu-0.0.0.dist-info/METADATA
os_cpu-0.0.0.dist-info/RECORD
os_cpu-0.0.0.dist-info/WHEEL
os_cpu-0.0.0.dist-info/metadata.json
os_cpu-0.0.0.dist-info/pbr.json
os_cpu-0.0.0.dist-info/top_level.txt
